cloudio/__init__.py
cloudio/common/__init__.py
cloudio/common/version.py
cloudio/common/core/__init__.py
cloudio/common/core/threaded.py
cloudio/common/mqtt/__init__.py
cloudio/common/mqtt/helpers.py
cloudio/common/mqtt/pending_update.py
cloudio/common/utils/__init__.py
cloudio/common/utils/attribute_helpers.py
cloudio/common/utils/datetime_helpers.py
cloudio/common/utils/path_helpers.py
cloudio/common/utils/resource_loader.py
cloudio/common/utils/string_helpers.py
cloudio/common/utils/timestamp_helpers.py
cloudio_common_python-2.0.0.dist-info/LICENSE
cloudio_common_python-2.0.0.dist-info/METADATA
cloudio_common_python-2.0.0.dist-info/WHEEL
cloudio_common_python-2.0.0.dist-info/top_level.txt
cloudio_common_python-2.0.0.dist-info/RECORD
